pywikipedia/__init__.py
pywikipedia/wikipedia.py
pywikipedia-0.0.1.dist-info/METADATA
pywikipedia-0.0.1.dist-info/RECORD
pywikipedia-0.0.1.dist-info/WHEEL
pywikipedia-0.0.1.dist-info/top_level.txt
