Metadata-Version: 2.1
Name: pywikipedia
Version: 0.0.1
Summary: Package for working wokring with wikipeida
Home-page: https://github.com/kaleidagraph/pywikipedia
Author: Kaleidagraph
Author-email: ben.webb.alpha@gmail.com
License: UNKNOWN
Platform: UNKNOWN
Classifier: Programming Language :: Python :: 3
Classifier: License :: OSI Approved :: MIT License
Classifier: Operating System :: OS Independent
